<?xml version="1.0"?>
<!-- 
    $Id$
	This file is part of the pyX12 project.

    Copyright (c) 2001-2004 Kalamazoo Community Mental Health Services,
		John Holland <jholland@kazoocmh.org> <john@zoner.org>

    All rights reserved.

	Redistribution and use in source and binary forms, with or without modification, 
	are permitted provided that the following conditions are met:

	1. Redistributions of source code must retain the above copyright notice, this list 
	   of conditions and the following disclaimer. 
	
	2. Redistributions in binary form must reproduce the above copyright notice, this 
	   list of conditions and the following disclaimer in the documentation and/or other 
	   materials provided with the distribution. 
	
	3. The name of the author may not be used to endorse or promote products derived 
	   from this software without specific prior written permission. 

	THIS SOFTWARE IS PROVIDED BY THE AUTHOR ``AS IS'' AND ANY EXPRESS OR IMPLIED 
	WARRANTIES, INCLUDING, BUT NOT LIMITED TO, THE IMPLIED WARRANTIES OF 
	MERCHANTABILITY AND FITNESS FOR A PARTICULAR PURPOSE ARE DISCLAIMED. IN NO 
	EVENT SHALL THE AUTHOR BE LIABLE FOR ANY DIRECT, INDIRECT, INCIDENTAL, SPECIAL, 
	EXEMPLARY, OR CONSEQUENTIAL DAMAGES (INCLUDING, BUT NOT LIMITED TO, PROCUREMENT 
	OF SUBSTITUTE GOODS OR SERVICES; LOSS OF USE, DATA, OR PROFITS; OR BUSINESS 
	INTERRUPTION) HOWEVER CAUSED AND ON ANY THEORY OF LIABILITY, WHETHER IN 
	CONTRACT, STRICT LIABILITY, OR TORT (INCLUDING NEGLIGENCE OR OTHERWISE) 
	ARISING IN ANY WAY OUT OF THE USE OF THIS SOFTWARE, EVEN IF ADVISED OF 
	THE POSSIBILITY OF SUCH DAMAGE.
-->
<map>
  <subcommittee>X12N</subcommittee>
  <version>00401</version>
  <loop type="explicit">
    <id>ISA</id>
    <name>Interchange Control Header</name>
    <usage>R</usage>
    <seq>001</seq>
    <pos>1</pos>
    <repeat>&gt;1</repeat>
    <segment>
      <id>ISA</id>
      <name>Interchange Control Header</name>
      <end_tag>IEA</end_tag>
      <usage>R</usage>
      <pos>1</pos>
      <element>
        <data_ele>I01</data_ele>
        <name>Authorization Information Qualifier</name>
        <usage>R</usage>
        <seq>01</seq>
        <refdes>ISA01</refdes>
        <data_type>ID</data_type>
        <min_len>2</min_len>
        <max_len>2</max_len>
        <valid_codes>
          <code>00</code>
          <code>03</code>
        </valid_codes>
      </element>
      <element>
        <data_ele>I02</data_ele>
        <name>Authorization Information</name>
        <usage>R</usage>
        <seq>02</seq>
        <refdes>ISA02</refdes>
        <data_type>AN</data_type>
        <min_len>10</min_len>
        <max_len>10</max_len>
      </element>
      <element>
        <data_ele>I03</data_ele>
        <name>Security Information Qualifier</name>
        <usage>R</usage>
        <seq>03</seq>
        <refdes>ISA03</refdes>
        <data_type>ID</data_type>
        <min_len>2</min_len>
        <max_len>2</max_len>
        <valid_codes>
          <code>00</code>
          <code>01</code>
        </valid_codes>
      </element>
      <element>
        <data_ele>I04</data_ele>
        <name>Security Information</name>
        <usage>R</usage>
        <seq>04</seq>
        <refdes>ISA04</refdes>
        <data_type>AN</data_type>
        <min_len>10</min_len>
        <max_len>10</max_len>
      </element>
      <element>
        <data_ele>I05</data_ele>
        <name>Interchange ID Qualifier</name>
        <usage>R</usage>
        <seq>05</seq>
        <refdes>ISA05</refdes>
        <data_type>ID</data_type>
        <min_len>2</min_len>
        <max_len>2</max_len>
        <valid_codes>
          <code>01</code>
          <code>14</code>
          <code>20</code>
          <code>27</code>
          <code>28</code>
          <code>29</code>
          <code>30</code>
          <code>33</code>
          <code>ZZ</code>
        </valid_codes>
      </element>
      <element>
        <data_ele>I06</data_ele>
        <name>Interchange Sender ID</name>
        <usage>R</usage>
        <seq>06</seq>
        <refdes>ISA06</refdes>
        <data_type>AN</data_type>
        <min_len>15</min_len>
        <max_len>15</max_len>
      </element>
      <element>
        <data_ele>I05</data_ele>
        <name>Interchange ID Qualifier</name>
        <usage>R</usage>
        <seq>07</seq>
        <refdes>ISA07</refdes>
        <data_type>ID</data_type>
        <min_len>2</min_len>
        <max_len>2</max_len>
        <valid_codes>
          <code>01</code>
          <code>14</code>
          <code>20</code>
          <code>27</code>
          <code>28</code>
          <code>29</code>
          <code>30</code>
          <code>33</code>
          <code>ZZ</code>
        </valid_codes>
      </element>
      <element>
        <data_ele>I07</data_ele>
        <name>Interchange Receiver ID</name>
        <usage>R</usage>
        <seq>08</seq>
        <refdes>ISA08</refdes>
        <data_type>AN</data_type>
        <min_len>15</min_len>
        <max_len>15</max_len>
      </element>
      <element>
        <data_ele>I08</data_ele>
        <name>Interchange Date</name>
        <usage>R</usage>
        <seq>09</seq>
        <refdes>ISA09</refdes>
        <data_type>DT</data_type>
        <min_len>6</min_len>
        <max_len>6</max_len>
        <format>D6</format>
      </element>
      <element>
        <data_ele>I09</data_ele>
        <name>Interchange Time</name>
        <usage>R</usage>
        <seq>10</seq>
        <refdes>ISA10</refdes>
        <data_type>TM</data_type>
        <min_len>4</min_len>
        <max_len>4</max_len>
        <format>TM</format>
      </element>
      <element>
        <data_ele>I10</data_ele>
        <name>Interchange Control Standards Identifier</name>
        <usage>R</usage>
        <seq>11</seq>
        <refdes>ISA11</refdes>
        <data_type>ID</data_type>
        <min_len>1</min_len>
        <max_len>1</max_len>
        <valid_codes>
          <code>U</code>
        </valid_codes>
      </element>
      <element>
        <data_ele>I11</data_ele>
        <name>Interchange Control Version Number</name>
        <usage>R</usage>
        <seq>12</seq>
        <refdes>ISA12</refdes>
        <data_type>ID</data_type>
        <min_len>5</min_len>
        <max_len>5</max_len>
        <valid_codes>
          <code>00401</code>
        </valid_codes>
      </element>
      <element>
        <data_ele>I12</data_ele>
        <name>Interchange Control Number</name>
        <usage>R</usage>
        <seq>13</seq>
        <refdes>ISA13</refdes>
        <data_type>N0</data_type>
        <min_len>9</min_len>
        <max_len>9</max_len>
      </element>
      <element>
        <data_ele>I13</data_ele>
        <name>Acknowledgment Requested</name>
        <usage>R</usage>
        <seq>14</seq>
        <refdes>ISA14</refdes>
        <data_type>ID</data_type>
        <min_len>1</min_len>
        <max_len>1</max_len>
        <valid_codes>
          <code>0</code>
          <code>1</code>
        </valid_codes>
      </element>
      <element>
        <data_ele>I14</data_ele>
        <name>Usage Indicator</name>
        <usage>R</usage>
        <seq>15</seq>
        <refdes>ISA15</refdes>
        <data_type>ID</data_type>
        <min_len>1</min_len>
        <max_len>1</max_len>
        <valid_codes>
          <code>P</code>
          <code>T</code>
        </valid_codes>
      </element>
      <element>
        <data_ele>I15</data_ele>
        <name>Component Element Separator</name>
        <usage>R</usage>
        <seq>16</seq>
        <refdes>ISA16</refdes>
        <data_type/>
        <min_len>1</min_len>
        <max_len>1</max_len>
      </element>
    </segment>
    <loop type="explicit">
      <id>GS</id>
      <name>Functional Group Header</name>
      <usage>R</usage>
      <seq>001</seq>
      <pos>2</pos>
      <repeat>&gt;1</repeat>
      <segment>
        <id>GS</id>
        <name>Functional Group Header</name>
        <end_tag>GE</end_tag>
        <usage>R</usage>
        <pos>1</pos>
        <element>
          <data_ele>479</data_ele>
          <name>Functional Identifier Code</name>
          <usage>R</usage>
          <seq>01</seq>
          <refdes>GS01</refdes>
          <data_type>ID</data_type>
          <min_len>2</min_len>
          <max_len>2</max_len>
          <valid_codes>
            <code>HN</code>
            <code>HR</code>
            <code>HS</code>
            <code>HB</code>
            <code>HI</code>
            <code>RA</code>
            <code>BE</code>
            <code>HP</code>
            <code>HC</code>
            <code>FA</code>
          </valid_codes>
        </element>
        <element>
          <data_ele>142</data_ele>
          <name>Application Sender's Code</name>
          <usage>R</usage>
          <seq>02</seq>
          <refdes>GS02</refdes>
          <data_type>AN</data_type>
          <min_len>2</min_len>
          <max_len>15</max_len>
        </element>
        <element>
          <data_ele>124</data_ele>
          <name>Application Receiver's Code</name>
          <usage>R</usage>
          <seq>03</seq>
          <refdes>GS03</refdes>
          <data_type>AN</data_type>
          <min_len>2</min_len>
          <max_len>15</max_len>
        </element>
        <element>
          <data_ele>373</data_ele>
          <name>Date</name>
          <usage>R</usage>
          <seq>04</seq>
          <refdes>GS04</refdes>
          <data_type>DT</data_type>
          <min_len>8</min_len>
          <max_len>8</max_len>
          <format>D8</format>
        </element>
        <element>
          <data_ele>337</data_ele>
          <name>Time</name>
          <usage>R</usage>
          <seq>05</seq>
          <refdes>GS05</refdes>
          <data_type>TM</data_type>
          <min_len>4</min_len>
          <max_len>8</max_len>
        </element>
        <element>
          <data_ele>28</data_ele>
          <name>Group Control Number</name>
          <usage>R</usage>
          <seq>06</seq>
          <refdes>GS06</refdes>
          <data_type>N0</data_type>
          <min_len>1</min_len>
          <max_len>9</max_len>
        </element>
        <element>
          <data_ele>455</data_ele>
          <name>Responsible Agency Code</name>
          <usage>R</usage>
          <seq>07</seq>
          <refdes>GS07</refdes>
          <data_type>ID</data_type>
          <min_len>1</min_len>
          <max_len>2</max_len>
          <valid_codes>
            <code>X</code>
          </valid_codes>
        </element>
        <element>
          <data_ele>480</data_ele>
          <name>Version / Release / Industry Identifier Code</name>
          <usage>R</usage>
          <seq>08</seq>
          <refdes>GS08</refdes>
          <data_type>AN</data_type>
          <min_len>1</min_len>
          <max_len>12</max_len>
          <valid_codes>
            <code>004010</code>
            <code>004010X093</code>
            <code>004010X092</code>
            <code>004010X094</code>
            <code>004010X061</code>
            <code>004010X095</code>
            <code>004010X091</code>
            <code>004010X096</code>
            <code>004010X097</code>
            <code>004010X098</code>
            <code>004010X093A1</code>
            <code>004010X092A1</code>
            <code>004010X094A1</code>
            <code>004010X061A1</code>
            <code>004010X095A1</code>
            <code>004010X091A1</code>
            <code>004010X096A1</code>
            <code>004010X097A1</code>
            <code>004010X098A1</code>
          </valid_codes>
        </element>
      </segment>
      <segment>
        <id>GE</id>
        <name>Functional Group Trailer</name>
        <usage>R</usage>
        <pos>4</pos>
        <element>
          <data_ele>97</data_ele>
          <name>Number of Transaction Sets Included</name>
          <usage>R</usage>
          <seq>01</seq>
          <refdes>GE01</refdes>
          <data_type>N0</data_type>
          <min_len>1</min_len>
          <max_len>6</max_len>
        </element>
        <element>
          <data_ele>28</data_ele>
          <name>Group Control Number</name>
          <usage>R</usage>
          <seq>02</seq>
          <refdes>GE02</refdes>
          <data_type>N0</data_type>
          <min_len>1</min_len>
          <max_len>9</max_len>
        </element>
      </segment>
    </loop>
    <segment>
      <id>TA1</id>
      <name>Interchange Achnowledgement</name>
      <usage>S</usage>
      <pos>2</pos>
      <element>
        <data_ele>I12</data_ele>
        <name>Interchange Control Number</name>
        <usage>R</usage>
        <seq>01</seq>
        <refdes>TA101</refdes>
        <data_type>N0</data_type>
        <min_len>9</min_len>
        <max_len>9</max_len>
      </element>
      <element>
        <data_ele>I08</data_ele>
        <name>Interchange Date</name>
        <usage>R</usage>
        <seq>02</seq>
        <refdes>TA102</refdes>
        <data_type>DT</data_type>
        <min_len>6</min_len>
        <max_len>6</max_len>
      </element>
      <element>
        <data_ele>I09</data_ele>
        <name>Interchange Time</name>
        <usage>R</usage>
        <seq>03</seq>
        <refdes>TA103</refdes>
        <data_type>TM</data_type>
        <min_len>4</min_len>
        <max_len>4</max_len>
      </element>
      <element>
        <data_ele>I17</data_ele>
        <name>Interchange Achnowledgement Code</name>
        <usage>R</usage>
        <seq>04</seq>
        <refdes>TA104</refdes>
        <data_type>ID</data_type>
        <min_len>1</min_len>
        <max_len>1</max_len>
        <valid_codes>
          <code>A</code>
          <code>E</code>
          <code>R</code>
        </valid_codes>
      </element>
      <element>
        <data_ele>I18</data_ele>
        <name>Interchange Note Code</name>
        <usage>R</usage>
        <seq>05</seq>
        <refdes>TA105</refdes>
        <data_type>ID</data_type>
        <min_len>3</min_len>
        <max_len>3</max_len>
        <valid_codes>
          <code>000</code>
          <code>001</code>
          <code>002</code>
          <code>003</code>
          <code>004</code>
          <code>005</code>
          <code>006</code>
          <code>007</code>
          <code>008</code>
          <code>009</code>
          <code>010</code>
          <code>011</code>
          <code>012</code>
          <code>013</code>
          <code>014</code>
          <code>015</code>
          <code>016</code>
          <code>017</code>
          <code>018</code>
          <code>019</code>
          <code>020</code>
          <code>021</code>
          <code>022</code>
          <code>023</code>
          <code>024</code>
          <code>025</code>
          <code>026</code>
          <code>027</code>
          <code>028</code>
          <code>029</code>
          <code>030</code>
          <code>031</code>
        </valid_codes>
      </element>
    </segment>
    <segment>
      <id>IEA</id>
      <name>Interchange Control Trailer</name>
      <usage>R</usage>
      <pos>3</pos>
      <element>
        <data_ele>I16</data_ele>
        <name>Number of Included Functional Groups</name>
        <usage>R</usage>
        <seq>01</seq>
        <refdes>IEA01</refdes>
        <data_type>N0</data_type>
        <min_len>1</min_len>
        <max_len>5</max_len>
      </element>
      <element>
        <data_ele>I12</data_ele>
        <name>Interchange Control Number</name>
        <usage>R</usage>
        <seq>02</seq>
        <refdes>IEA02</refdes>
        <data_type>N0</data_type>
        <min_len>9</min_len>
        <max_len>9</max_len>
      </element>
    </segment>
  </loop>
</map>
